nivel1/nivel2/magnetron/nivel_3/latch/latch.v
module latch_sr(input S, input R, 
                output reg Q);

always@*
    if (S && !R) //Set
        Q <= 1'b1;
    else if (R && !S) //Reset
        Q <= 1'b0;

endmodule

nivel1/nivel_2/controle_magnetron/nivel_3/latch/latch.tb.v
`timescale 1ns/1ps

module test_latch;

    reg S, R;
    wire Q;

    latch_sr DUT(S, R, Q);

    initial begin
        $dumpfile("latch_teste.vcd");
        $dumpvars(0,test_latch);
            #10 S = 0; R = 0;

            #10 S = 0; R = 0; 

            #10 S = 0; R = 1; 

            #10 S = 0; R = 1;

            #10 S = 0; R = 0;

            #10 S = 0; R = 0;

            #10 S = 1; R = 0; 

            #10 S = 1; R = 0;

            #10 S = 0; R = 0;

            #10 S = 0; R = 0;

            #10 S = 1; R = 1;

            #10 S = 1; R = 1;

            #10 S = 0; R = 0; 

            #10 S = 0; R = 0;

            #10;
    end
endmodule

nivel1/nivel_2/controle_magnetron/nivel_3/latch/latch_teste.vcd
$date
	Sun Apr 23 17:36:53 2023
$end
$version
	Icarus Verilog
$end
$timescale
	1ps
$end
$scope module test_latch $end
$var wire 1 ! Q $end
$var reg 1 " R $end
$var reg 1 # S $end
$scope module DUT $end
$var wire 1 " R $end
$var wire 1 # S $end
$var reg 1 ! Q $end
$upscope $end
$upscope $end
$enddefinitions $end
$comment Show the parameter values. $end
$dumpall
$end
#0
$dumpvars
x#
x"
x!
$end
#10000
0"
0#
#30000
0!
1"
#50000
0"
#70000
1!
1#
#90000
0#
#110000
1"
1#
#130000
0"
0#
