contador_mod10/contador_mod10.v
module contador_mod10 (data, clk, load, enable, clear, count, count_end, tc);
  input wire [3:0] data;
  input wire clk, load, enable, clear;
  output reg [3:0] count;
  output wire count_end;
  output wire tc;

  always @ (negedge clear)
  begin
    count <= 4'b0000;
  end
  assign tc = enable & count_end;
  always @ (posedge clk)
  begin
    if (enable) begin
      case (count)
        4'b0000: count <= 4'b1001;
        default: count <= count - 4'b0001;
      endcase
    end
    else begin
      if (!load) begin
        count <= data;
      end
    end
  end
  
  assign count_end = (count == 4'b0000) ? 1'b1 : 1'b0;
endmodule

contador_mod_6/contador_mod_6.v
module contador_mod_6(data, clk, loadn, en, clearn, tens, tc, zero);
  input wire [3:0] data;
  input wire clk, loadn, en, clearn;
  output reg [3:0] tens;
  output wire tc;
  output wire zero;

  always @ (negedge clearn)
  begin
    tens = 4'b0000;
  end

  assign zero = (tens == 4'b0000) ? 1'b1 : 1'b0;
  assign tc = en & zero;

  always @ (posedge clk)
  begin
    if (en) 
      case (tens)
        4'b0101: begin
          tens <= 4'b0100;
        end // 5 -> 4
        4'b0001: begin 
          tens <= 4'b0000;
        end  // 1 -> 0
        4'b0000: begin
          tens <= 4'b0101;
        end // 0 -> 5
        default: tens <= tens - 4'b0001;
      endcase

    else begin

      if(!loadn)
        tens <= data;
    end
  end
endmodule

nivel1/nivel2/timer/timer.v
`include "./nivel3/contador_mod10/contador_mod10.v"
`include "./nivel3/contador_mod6/contador_mod6.v"
`timescale 1ns/1ns

module timer_nivel2(
    input [3:0] data,
    input wire enable, clk, load, clearn,
    output wire zero,
    output wire [3:0] so, st, min
);

    wire t1, t2, t3, ze1, ze2, ze3;

    contador_mod10 secs(data, clk, load, enable, clearn, so, t1, ze1);
    contador_mod_6 tens(data, clk, load, enable, clearn, st, t2, ze2);
    contador_mod10 minutes(data, clk, load, enable, clearn, min, t3, ze3);

    assign zero = ze1 & ze2 & ze3;

endmodule

nivel1/nivel2/timer/timer.tb.v
`timescale 1ns/1ps

module timer_nivel2_teste;
    wire[3:0] so, st, min;
    wire zero;
    reg [3:0]  data;
    reg clearn, enable, loadn, clk;

    timer_nivel2 dut(data, enable, clk, load,
                  clearn, zero, so, st, min);

    initial begin
        $dumpfile("timer_nivel2_teste.vcd");
        $dumpvars(0,timer_nivel2_teste);
        clk  = 1'b0;
        enable = 1'b0; 
        loadn  = 1'b0;
    end

    always begin
        #1 clk = loadn? ~clk : clk;
    end

    initial begin    

        clearn = 1'b1; #0.5
        clearn = 1'b0; #0.5
        clearn = 1'b1; #0.5

        data =  2;   #0.04;
        clk = 1'b1;   #0.01;
        clk = 1'b0;   #0.95;

        data =  1;   #0.04;
        clk = 1'b1;   #0.01;
        clk = 1'b0;   #0.95;

        data =  7;   #0.04;
        clk = 1'b1;   #0.01;
        clk = 1'b0;   #0.95;

        data =  9;   #0.04;
        clk = 1'b1;   #0.01;
        clk = 1'b0;   #0.95;

        enable = 1; loadn = 1; #1000;

        $finish();
    end
endmodule

nivel1/nivel2/minutos_segundos/timer_nivel2_teste.vcd
$date
	Sat Apr 22 12:39:48 2023
$end
$version
	Icarus Verilog
$end
$timescale
	1ps
$end
$scope module timer_nivel2_teste $end
$var wire 1 ! load $end
$var wire 1 " zero $end
$var wire 4 # st [3:0] $end
$var wire 4 $ so [3:0] $end
$var wire 4 % min [3:0] $end
$var reg 1 & clearn $end
$var reg 1 ' clk $end
$var reg 4 ( data [3:0] $end
$var reg 1 ) enable $end
$var reg 1 * loadn $end
$scope module dut $end
$var wire 1 & clearn $end
$var wire 1 ' clk $end
$var wire 4 + data [3:0] $end
$var wire 1 ) enable $end
$var wire 1 ! load $end
$var wire 1 " zero $end
$var wire 1 , ze3 $end
$var wire 1 - ze2 $end
$var wire 1 . ze1 $end
$var wire 1 / t3 $end
$var wire 1 0 t2 $end
$var wire 1 1 t1 $end
$var wire 4 2 st [3:0] $end
$var wire 4 3 so [3:0] $end
$var wire 4 4 min [3:0] $end
$scope module minutes $end
$var wire 1 & clear $end
$var wire 1 ' clk $end
$var wire 4 5 data [3:0] $end
$var wire 1 ) enable $end
$var wire 1 ! load $end
$var wire 1 , tc $end
$var wire 1 / count_end $end
$var reg 4 6 count [3:0] $end
$upscope $end
$scope module secs $end
$var wire 1 & clear $end
$var wire 1 ' clk $end
$var wire 4 7 data [3:0] $end
$var wire 1 ) enable $end
$var wire 1 ! load $end
$var wire 1 . tc $end
$var wire 1 1 count_end $end
$var reg 4 8 count [3:0] $end
$upscope $end
$scope module tens $end
$var wire 1 & clearn $end
$var wire 1 ' clk $end
$var wire 4 9 data [3:0] $end
$var wire 1 ) en $end
$var wire 1 ! loadn $end
$var wire 1 0 tc $end
$var wire 1 - zero $end
$var reg 4 : tens [3:0] $end
$upscope $end
$upscope $end
$upscope $end
$enddefinitions $end
$comment Show the parameter values. $end
$dumpall
$end
#0
$dumpvars
bx :
bx 9
bx 8
bx 7
bx 6
bx 5
bx 4
bx 3
bx 2
x1
00
x/
0.
x-
0,
bx +
0*
0)
bx (
0'
1&
bx %
bx $
bx #
0"
z!
$end
#500
11
1/
b0 $
b0 3
b0 8
b0 %
b0 4
b0 6
1-
b0 #
b0 2
b0 :
0&
#1000
1&
#1500
b10 (
b10 +
b10 5
b10 7
b10 9
#1540
1'
#1550
0'
#2500
b1 (
b1 +
b1 5
b1 7
b1 9
#2540
1'
#2550
0'
#3500
b111 (
b111 +
b111 5
b111 7
b111 9
#3540
1'
#3550
0'
#4500
b1001 (
b1001 +
b1001 5
b1001 7
b1001 9
#4540
1'
#4550
0'
#5500
1"
1,
1.
10
1*
1)
#6000
0"
0.
00
0,
01
0-
0/
b1001 $
b1001 3
b1001 8
b101 #
b101 2
b101 :
b1001 %
b1001 4
b1001 6
1'
#7000
0'
#8000
b1000 %
b1000 4
b1000 6
b100 #
b100 2
b100 :
b1000 $
b1000 3
b1000 8
1'
#9000
0'
#10000
b111 $
b111 3
b111 8
b11 #
b11 2
b11 :
b111 %
b111 4
b111 6
1'
#11000
0'
#12000
b110 %
b110 4
b110 6
b10 #
b10 2
b10 :
b110 $
b110 3
b110 8
1'
#13000
0'
#14000
b101 $
b101 3
b101 8
b1 #
b1 2
b1 :
b101 %
b101 4
b101 6
1'
#15000
0'
#16000
10
1-
b100 %
b100 4
b100 6
b0 #
b0 2
b0 :
b100 $
b100 3
b100 8
1'
#17000
0'
#18000
00
0-
b11 $
b11 3
b11 8
b101 #
b101 2
b101 :
b11 %
b11 4
b11 6
1'
#19000
0'
#20000
b10 %
b10 4
b10 6
b100 #
b100 2
b100 :
b10 $
b10 3
b10 8
1'
#21000
0'
#22000
b1 $
b1 3
b1 8
b11 #
b11 2
b11 :
b1 %
b1 4
b1 6
1'
#23000
0'
#24000
1,
1.
1/
11
b0 %
b0 4
b0 6
b10 #
b10 2
b10 :
b0 $
b0 3
b0 8
1'
#25000
0'
#26000
0.
0,
01
0/
b1001 $
b1001 3
b1001 8
b1 #
b1 2
b1 :
b1001 %
b1001 4
b1001 6
1'
#27000
0'
#28000
10
1-
b1000 %
b1000 4
b1000 6
b0 #
b0 2
b0 :
b1000 $
b1000 3
b1000 8
1'
#29000
0'
#30000
00
0-
b111 $
b111 3
b111 8
b101 #
b101 2
b101 :
b111 %
b111 4
b111 6
1'
#31000
0'
#32000
b110 %
b110 4
b110 6
b100 #
b100 2
b100 :
b110 $
b110 3
b110 8
1'
#33000
0'
#34000
b101 $
b101 3
b101 8
b11 #
b11 2
b11 :
b101 %
b101 4
b101 6
1'
#35000
0'
#36000
b100 %
b100 4
b100 6
b10 #
b10 2
b10 :
b100 $
b100 3
b100 8
1'
#37000
0'
#38000
b11 $
b11 3
b11 8
b1 #
b1 2
b1 :
b11 %
b11 4
b11 6
1'
#39000
0'
#40000
10
1-
b10 %
b10 4
b10 6
b0 #
b0 2
b0 :
b10 $
b10 3
b10 8
1'
#41000
0'
#42000
00
0-
b1 $
b1 3
b1 8
b101 #
b101 2
b101 :
b1 %
b1 4
b1 6
1'
#43000
0'
#44000
1,
1.
1/
11
b0 %
b0 4
b0 6
b100 #
b100 2
b100 :
b0 $
b0 3
b0 8
1'
#45000
0'
#46000
0.
0,
01
0/
b1001 $
b1001 3
b1001 8
b11 #
b11 2
b11 :
b1001 %
b1001 4
b1001 6
1'
#47000
0'
#48000
b1000 %
b1000 4
b1000 6
b10 #
b10 2
b10 :
b1000 $
b1000 3
b1000 8
1'
#49000
0'
#50000
b111 $
b111 3
b111 8
b1 #
b1 2
b1 :
b111 %
b111 4
b111 6
1'
#51000
0'
#52000
10
1-
b110 %
b110 4
b110 6
b0 #
b0 2
b0 :
b110 $
b110 3
b110 8
1'
#53000
0'
#54000
00
0-
b101 $
b101 3
b101 8
b101 #
b101 2
b101 :
b101 %
b101 4
b101 6
1'
#55000
0'
#56000
b100 %
b100 4
b100 6
b100 #
b100 2
b100 :
b100 $
b100 3
b100 8
1'
#57000
0'
#58000
b11 $
b11 3
b11 8
b11 #
b11 2
b11 :
b11 %
b11 4
b11 6
1'
#59000
0'
#60000
b10 %
b10 4
b10 6
b10 #
b10 2
b10 :
b10 $
b10 3
b10 8
1'
#61000
0'
#62000
b1 $
b1 3
b1 8
b1 #
b1 2
b1 :
b1 %
b1 4
b1 6
1'
#63000
0'
#64000
1"
1,
10
1.
1/
1-
11
b0 %
b0 4
b0 6
b0 #
b0 2
b0 :
b0 $
b0 3
b0 8
1'
#65000
0'
#66000
0"
0.
00
0,
01
0-
0/
b1001 $
b1001 3
b1001 8
b101 #
b101 2
b101 :
b1001 %
b1001 4
b1001 6
1'
#67000
0'
#68000
b1000 %
b1000 4
b1000 6
b100 #
b100 2
b100 :
b1000 $
b1000 3
b1000 8
1'
#69000
0'
#70000
b111 $
b111 3
b111 8
b11 #
b11 2
b11 :
b111 %
b111 4
b111 6
1'
#71000
0'
#72000
b110 %
b110 4
b110 6
b10 #
b10 2
b10 :
b110 $
b110 3
b110 8
1'
#73000
0'
#74000
b101 $
b101 3
b101 8
b1 #
b1 2
b1 :
b101 %
b101 4
b101 6
1'
#75000
0'
#76000
10
1-
b100 %
b100 4
b100 6
b0 #
b0 2
b0 :
b100 $
b100 3
b100 8
1'
#77000
0'
#78000
00
0-
b11 $
b11 3
b11 8
b101 #
b101 2
b101 :
b11 %
b11 4
b11 6
1'
#79000
0'
#80000
b10 %
b10 4
b10 6
b100 #
b100 2
b100 :
b10 $
b10 3
b10 8
1'
#81000
0'
#82000
b1 $
b1 3
b1 8
b11 #
b11 2
b11 :
b1 %
b1 4
b1 6
1'
#83000
0'
#84000
1,
1.
1/
11
b0 %
b0 4
b0 6
b10 #
b10 2
b10 :
b0 $
b0 3
b0 8
1'
#85000
0'
#86000
0.
0,
01
0/
b1001 $
b1001 3
b1001 8
b1 #
b1 2
b1 :
b1001 %
b1001 4
b1001 6
1'
#87000
0'
#88000
10
1-
b1000 %
b1000 4
b1000 6
b0 #
b0 2
b0 :
b1000 $
b1000 3
b1000 8
1'
#89000
0'
#90000
00
0-
b111 $
b111 3
b111 8
b101 #
b101 2
b101 :
b111 %
b111 4
b111 6
1'
#91000
0'
#92000
b110 %
b110 4
b110 6
b100 #
b100 2
b100 :
b110 $
b110 3
b110 8
1'
#93000
0'
#94000
b101 $
b101 3
b101 8
b11 #
b11 2
b11 :
b101 %
b101 4
b101 6
1'
#95000
0'
#96000
b100 %
b100 4
b100 6
b10 #
b10 2
b10 :
b100 $
b100 3
b100 8
1'
#97000
0'
#98000
b11 $
b11 3
b11 8
b1 #
b1 2
b1 :
b11 %
b11 4
b11 6
1'
#99000
0'
#100000
10
1-
b10 %
b10 4
b10 6
b0 #
b0 2
b0 :
b10 $
b10 3
b10 8
1'
#101000
0'
#102000
00
0-
b1 $
b1 3
b1 8
b101 #
b101 2
b101 :
b1 %
b1 4
b1 6
1'
#103000
0'
#104000
1,
1.
1/
11
b0 %
b0 4
b0 6
b100 #
b100 2
b100 :
b0 $
b0 3
b0 8
1'
#105000
0'
#106000
0.
0,
01
0/
b1001 $
b1001 3
b1001 8
b11 #
b11 2
b11 :
b1001 %
b1001 4
b1001 6
1'
#107000
0'
#108000
b1000 %
b1000 4
b1000 6
b10 #
b10 2
b10 :
b1000 $
b1000 3
b1000 8
1'
#109000
0'
#110000
b111 $
b111 3
b111 8
b1 #
b1 2
b1 :
b111 %
b111 4
b111 6
1'
#111000
0'
#112000
10
1-
b110 %
b110 4
b110 6
b0 #
b0 2
b0 :
b110 $
b110 3
b110 8
1'
#113000
0'
#114000
00
0-
b101 $
b101 3
b101 8
b101 #
b101 2
b101 :
b101 %
b101 4
b101 6
1'
#115000
0'
#116000
b100 %
b100 4
b100 6
b100 #
b100 2
b100 :
b100 $
b100 3
b100 8
1'
#117000
0'
#118000
b11 $
b11 3
b11 8
b11 #
b11 2
b11 :
b11 %
b11 4
b11 6
1'
#119000
0'
#120000
b10 %
b10 4
b10 6
b10 #
b10 2
b10 :
b10 $
b10 3
b10 8
1'
#121000
0'
#122000
b1 $
b1 3
b1 8
b1 #
b1 2
b1 :
b1 %
b1 4
b1 6
1'
#123000
0'
#124000
1"
1,
10
1.
1/
1-
11
b0 %
b0 4
b0 6
b0 #
b0 2
b0 :
b0 $
b0 3
b0 8
1'
#125000
0'
#126000
0"
0.
00
0,
01
0-
0/
b1001 $
b1001 3
b1001 8
b101 #
b101 2
b101 :
b1001 %
b1001 4
b1001 6
1'
#127000
0'
#128000
b1000 %
b1000 4
b1000 6
b100 #
b100 2
b100 :
b1000 $
b1000 3
b1000 8
1'
#129000
0'
#130000
b111 $
b111 3
b111 8
b11 #
b11 2
b11 :
b111 %
b111 4
b111 6
1'
#131000
0'
#132000
b110 %
b110 4
b110 6
b10 #
b10 2
b10 :
b110 $
b110 3
b110 8
1'
#133000
0'
#134000
b101 $
b101 3
b101 8
b1 #
b1 2
b1 :
b101 %
b101 4
b101 6
1'
#135000
0'
#136000
10
1-
b100 %
b100 4
b100 6
b0 #
b0 2
b0 :
b100 $
b100 3
b100 8
1'
#137000
0'
#138000
00
0-
b11 $
b11 3
b11 8
b101 #
b101 2
b101 :
b11 %
b11 4
b11 6
1'
#139000
0'
#140000
b10 %
b10 4
b10 6
b100 #
b100 2
b100 :
b10 $
b10 3
b10 8
1'
#141000
0'
#142000
b1 $
b1 3
b1 8
b11 #
b11 2
b11 :
b1 %
b1 4
b1 6
1'
#143000
0'
#144000
1,
1.
1/
11
b0 %
b0 4
b0 6
b10 #
b10 2
b10 :
b0 $
b0 3
b0 8
1'
#145000
0'
#146000
0.
0,
01
0/
b1001 $
b1001 3
b1001 8
b1 #
b1 2
b1 :
b1001 %
b1001 4
b1001 6
1'
#147000
0'
#148000
10
1-
b1000 %
b1000 4
b1000 6
b0 #
b0 2
b0 :
b1000 $
b1000 3
b1000 8
1'
#149000
0'
#150000
00
0-
b111 $
b111 3
b111 8
b101 #
b101 2
b101 :
b111 %
b111 4
b111 6
1'
#151000
0'
#152000
b110 %
b110 4
b110 6
b100 #
b100 2
b100 :
b110 $
b110 3
b110 8
1'
#153000
0'
#154000
b101 $
b101 3
b101 8
b11 #
b11 2
b11 :
b101 %
b101 4
b101 6
1'
#155000
0'
#156000
b100 %
b100 4
b100 6
b10 #
b10 2
b10 :
b100 $
b100 3
b100 8
1'
#157000
0'
#158000
b11 $
b11 3
b11 8
b1 #
b1 2
b1 :
b11 %
b11 4
b11 6
1'
#159000
0'
#160000
10
1-
b10 %
b10 4
b10 6
b0 #
b0 2
b0 :
b10 $
b10 3
b10 8
1'
#161000
0'
#162000
00
0-
b1 $
b1 3
b1 8
b101 #
b101 2
b101 :
b1 %
b1 4
b1 6
1'
#163000
0'
#164000
1,
1.
1/
11
b0 %
b0 4
b0 6
b100 #
b100 2
b100 :
b0 $
b0 3
b0 8
1'
#165000
0'
#166000
0.
0,
01
0/
b1001 $
b1001 3
b1001 8
b11 #
b11 2
b11 :
b1001 %
b1001 4
b1001 6
1'
#167000
0'
#168000
b1000 %
b1000 4
b1000 6
b10 #
b10 2
b10 :
b1000 $
b1000 3
b1000 8
1'
#169000
0'
#170000
b111 $
b111 3
b111 8
b1 #
b1 2
b1 :
b111 %
b111 4
b111 6
1'
#171000
0'
#172000
10
1-
b110 %
b110 4
b110 6
b0 #
b0 2
b0 :
b110 $
b110 3
b110 8
1'
#173000
0'
#174000
00
0-
b101 $
b101 3
b101 8
b101 #
b101 2
b101 :
b101 %
b101 4
b101 6
1'
#175000
0'
#176000
b100 %
b100 4
b100 6
b100 #
b100 2
b100 :
b100 $
b100 3
b100 8
1'
#177000
0'
#178000
b11 $
b11 3
b11 8
b11 #
b11 2
b11 :
b11 %
b11 4
b11 6
1'
#179000
0'
#180000
b10 %
b10 4
b10 6
b10 #
b10 2
b10 :
b10 $
b10 3
b10 8
1'
#181000
0'
#182000
b1 $
b1 3
b1 8
b1 #
b1 2
b1 :
b1 %
b1 4
b1 6
1'
#183000
0'
#184000
1"
1,
10
1.
1/
1-
11
b0 %
b0 4
b0 6
b0 #
b0 2
b0 :
b0 $
b0 3
b0 8
1'
#185000
0'
#186000
0"
0.
00
0,
01
0-
0/
b1001 $
b1001 3
b1001 8
b101 #
b101 2
b101 :
b1001 %
b1001 4
b1001 6
1'
#187000
0'
#188000
b1000 %
b1000 4
b1000 6
b100 #
b100 2
b100 :
b1000 $
b1000 3
b1000 8
1'
#189000
0'
#190000
b111 $
b111 3
b111 8
b11 #
b11 2
b11 :
b111 %
b111 4
b111 6
1'
#191000
0'
#192000
b110 %
b110 4
b110 6
b10 #
b10 2
b10 :
b110 $
b110 3
b110 8
1'
#193000
0'
#194000
b101 $
b101 3
b101 8
b1 #
b1 2
b1 :
b101 %
b101 4
b101 6
1'
#195000
0'
#196000
10
1-
b100 %
b100 4
b100 6
b0 #
b0 2
b0 :
b100 $
b100 3
b100 8
1'
#197000
0'
#198000
00
0-
b11 $
b11 3
b11 8
b101 #
b101 2
b101 :
b11 %
b11 4
b11 6
1'
#199000
0'
#200000
b10 %
b10 4
b10 6
b100 #
b100 2
b100 :
b10 $
b10 3
b10 8
1'
#201000
0'
#202000
b1 $
b1 3
b1 8
b11 #
b11 2
b11 :
b1 %
b1 4
b1 6
1'
#203000
0'
#204000
1,
1.
1/
11
b0 %
b0 4
b0 6
b10 #
b10 2
b10 :
b0 $
b0 3
b0 8
1'
#205000
0'
#206000
0.
0,
01
0/
b1001 $
b1001 3
b1001 8
b1 #
b1 2
b1 :
b1001 %
b1001 4
b1001 6
1'
#207000
0'
#208000
10
1-
b1000 %
b1000 4
b1000 6
b0 #
b0 2
b0 :
b1000 $
b1000 3
b1000 8
1'
#209000
0'
#210000
00
0-
b111 $
b111 3
b111 8
b101 #
b101 2
b101 :
b111 %
b111 4
b111 6
1'
#211000
0'
#212000
b110 %
b110 4
b110 6
b100 #
b100 2
b100 :
b110 $
b110 3
b110 8
1'
#213000
0'
#214000
b101 $
b101 3
b101 8
b11 #
b11 2
b11 :
b101 %
b101 4
b101 6
1'
#215000
0'
#216000
b100 %
b100 4
b100 6
b10 #
b10 2
b10 :
b100 $
b100 3
b100 8
1'
#217000
0'
#218000
b11 $
b11 3
b11 8
b1 #
b1 2
b1 :
b11 %
b11 4
b11 6
1'
#219000
0'
#220000
10
1-
b10 %
b10 4
b10 6
b0 #
b0 2
b0 :
b10 $
b10 3
b10 8
1'
#221000
0'
#222000
00
0-
b1 $
b1 3
b1 8
b101 #
b101 2
b101 :
b1 %
b1 4
b1 6
1'
#223000
0'
#224000
1,
1.
1/
11
b0 %
b0 4
b0 6
b100 #
b100 2
b100 :
b0 $
b0 3
b0 8
1'
#225000
0'
#226000
0.
0,
01
0/
b1001 $
b1001 3
b1001 8
b11 #
b11 2
b11 :
b1001 %
b1001 4
b1001 6
1'
#227000
0'
#228000
b1000 %
b1000 4
b1000 6
b10 #
b10 2
b10 :
b1000 $
b1000 3
b1000 8
1'
#229000
0'
#230000
b111 $
b111 3
b111 8
b1 #
b1 2
b1 :
b111 %
b111 4
b111 6
1'
#231000
0'
#232000
10
1-
b110 %
b110 4
b110 6
b0 #
b0 2
b0 :
b110 $
b110 3
b110 8
1'
#233000
0'
#234000
00
0-
b101 $
b101 3
b101 8
b101 #
b101 2
b101 :
b101 %
b101 4
b101 6
1'
#235000
0'
#236000
b100 %
b100 4
b100 6
b100 #
b100 2
b100 :
b100 $
b100 3
b100 8
1'
#237000
0'
#238000
b11 $
b11 3
b11 8
b11 #
b11 2
b11 :
b11 %
b11 4
b11 6
1'
#239000
0'
#240000
b10 %
b10 4
b10 6
b10 #
b10 2
b10 :
b10 $
b10 3
b10 8
1'
#241000
0'
#242000
b1 $
b1 3
b1 8
b1 #
b1 2
b1 :
b1 %
b1 4
b1 6
1'
#243000
0'
#244000
1"
1,
10
1.
1/
1-
11
b0 %
b0 4
b0 6
b0 #
b0 2
b0 :
b0 $
b0 3
b0 8
1'
#245000
0'
#246000
0"
0.
00
0,
01
0-
0/
b1001 $
b1001 3
b1001 8
b101 #
b101 2
b101 :
b1001 %
b1001 4
b1001 6
1'
#247000
0'
#248000
b1000 %
b1000 4
b1000 6
b100 #
b100 2
b100 :
b1000 $
b1000 3
b1000 8
1'
#249000
0'
#250000
b111 $
b111 3
b111 8
b11 #
b11 2
b11 :
b111 %
b111 4
b111 6
1'
#251000
0'
#252000
b110 %
b110 4
b110 6
b10 #
b10 2
b10 :
b110 $
b110 3
b110 8
1'
#253000
0'
#254000
b101 $
b101 3
b101 8
b1 #
b1 2
b1 :
b101 %
b101 4
b101 6
1'
#255000
0'
#256000
10
1-
b100 %
b100 4
b100 6
b0 #
b0 2
b0 :
b100 $
b100 3
b100 8
1'
#257000
0'
#258000
00
0-
b11 $
b11 3
b11 8
b101 #
b101 2
b101 :
b11 %
b11 4
b11 6
1'
#259000
0'
#260000
b10 %
b10 4
b10 6
b100 #
b100 2
b100 :
b10 $
b10 3
b10 8
1'
#261000
0'
#262000
b1 $
b1 3
b1 8
b11 #
b11 2
b11 :
b1 %
b1 4
b1 6
1'
#263000
0'
#264000
1,
1.
1/
11
b0 %
b0 4
b0 6
b10 #
b10 2
b10 :
b0 $
b0 3
b0 8
1'
#265000
0'
#266000
0.
0,
01
0/
b1001 $
b1001 3
b1001 8
b1 #
b1 2
b1 :
b1001 %
b1001 4
b1001 6
1'
#267000
0'
#268000
10
1-
b1000 %
b1000 4
b1000 6
b0 #
b0 2
b0 :
b1000 $
b1000 3
b1000 8
1'
#269000
0'
#270000
00
0-
b111 $
b111 3
b111 8
b101 #
b101 2
b101 :
b111 %
b111 4
b111 6
1'
#271000
0'
#272000
b110 %
b110 4
b110 6
b100 #
b100 2
b100 :
b110 $
b110 3
b110 8
1'
#273000
0'
#274000
b101 $
b101 3
b101 8
b11 #
b11 2
b11 :
b101 %
b101 4
b101 6
1'
#275000
0'
#276000
b100 %
b100 4
b100 6
b10 #
b10 2
b10 :
b100 $
b100 3
b100 8
1'
#277000
0'
#278000
b11 $
b11 3
b11 8
b1 #
b1 2
b1 :
b11 %
b11 4
b11 6
1'
#279000
0'
#280000
10
1-
b10 %
b10 4
b10 6
b0 #
b0 2
b0 :
b10 $
b10 3
b10 8
1'
#281000
0'
#282000
00
0-
b1 $
b1 3
b1 8
b101 #
b101 2
b101 :
b1 %
b1 4
b1 6
1'
#283000
0'
#284000
1,
1.
1/
11
b0 %
b0 4
b0 6
b100 #
b100 2
b100 :
b0 $
b0 3
b0 8
1'
#285000
0'
#286000
0.
0,
01
0/
b1001 $
b1001 3
b1001 8
b11 #
b11 2
b11 :
b1001 %
b1001 4
b1001 6
1'
#287000
0'
#288000
b1000 %
b1000 4
b1000 6
b10 #
b10 2
b10 :
b1000 $
b1000 3
b1000 8
1'
#289000
0'
#290000
b111 $
b111 3
b111 8
b1 #
b1 2
b1 :
b111 %
b111 4
b111 6
1'
#291000
0'
#292000
10
1-
b110 %
b110 4
b110 6
b0 #
b0 2
b0 :
b110 $
b110 3
b110 8
1'
#293000
0'
#294000
00
0-
b101 $
b101 3
b101 8
b101 #
b101 2
b101 :
b101 %
b101 4
b101 6
1'
#295000
0'
#296000
b100 %
b100 4
b100 6
b100 #
b100 2
b100 :
b100 $
b100 3
b100 8
1'
#297000
0'
#298000
b11 $
b11 3
b11 8
b11 #
b11 2
b11 :
b11 %
b11 4
b11 6
1'
#299000
0'
#300000
b10 %
b10 4
b10 6
b10 #
b10 2
b10 :
b10 $
b10 3
b10 8
1'
#301000
0'
#302000
b1 $
b1 3
b1 8
b1 #
b1 2
b1 :
b1 %
b1 4
b1 6
1'
#303000
0'
#304000
1"
1,
10
1.
1/
1-
11
b0 %
b0 4
b0 6
b0 #
b0 2
b0 :
b0 $
b0 3
b0 8
1'
#305000
0'
#306000
0"
0.
00
0,
01
0-
0/
b1001 $
b1001 3
b1001 8
b101 #
b101 2
b101 :
b1001 %
b1001 4
b1001 6
1'
#307000
0'
#308000
b1000 %
b1000 4
b1000 6
b100 #
b100 2
b100 :
b1000 $
b1000 3
b1000 8
1'
#309000
0'
#310000
b111 $
b111 3
b111 8
b11 #
b11 2
b11 :
b111 %
b111 4
b111 6
1'
#311000
0'
#312000
b110 %
b110 4
b110 6
b10 #
b10 2
b10 :
b110 $
b110 3
b110 8
1'
#313000
0'
#314000
b101 $
b101 3
b101 8
b1 #
b1 2
b1 :
b101 %
b101 4
b101 6
1'
#315000
0'
#316000
10
1-
b100 %
b100 4
b100 6
b0 #
b0 2
b0 :
b100 $
b100 3
b100 8
1'
#317000
0'
#318000
00
0-
b11 $
b11 3
b11 8
b101 #
b101 2
b101 :
b11 %
b11 4
b11 6
1'
#319000
0'
#320000
b10 %
b10 4
b10 6
b100 #
b100 2
b100 :
b10 $
b10 3
b10 8
1'
#321000
0'
#322000
b1 $
b1 3
b1 8
b11 #
b11 2
b11 :
b1 %
b1 4
b1 6
1'
#323000
0'
#324000
1,
1.
1/
11
b0 %
b0 4
b0 6
b10 #
b10 2
b10 :
b0 $
b0 3
b0 8
1'
#325000
0'
#326000
0.
0,
01
0/
b1001 $
b1001 3
b1001 8
b1 #
b1 2
b1 :
b1001 %
b1001 4
b1001 6
1'
#327000
0'
#328000
10
1-
b1000 %
b1000 4
b1000 6
b0 #
b0 2
b0 :
b1000 $
b1000 3
b1000 8
1'
#329000
0'
#330000
00
0-
b111 $
b111 3
b111 8
b101 #
b101 2
b101 :
b111 %
b111 4
b111 6
1'
#331000
0'
#332000
b110 %
b110 4
b110 6
b100 #
b100 2
b100 :
b110 $
b110 3
b110 8
1'
#333000
0'
#334000
b101 $
b101 3
b101 8
b11 #
b11 2
b11 :
b101 %
b101 4
b101 6
1'
#335000
0'
#336000
b100 %
b100 4
b100 6
b10 #
b10 2
b10 :
b100 $
b100 3
b100 8
1'
#337000
0'
#338000
b11 $
b11 3
b11 8
b1 #
b1 2
b1 :
b11 %
b11 4
b11 6
1'
#339000
0'
#340000
10
1-
b10 %
b10 4
b10 6
b0 #
b0 2
b0 :
b10 $
b10 3
b10 8
1'
#341000
0'
#342000
00
0-
b1 $
b1 3
b1 8
b101 #
b101 2
b101 :
b1 %
b1 4
b1 6
1'
#343000
0'
#344000
1,
1.
1/
11
b0 %
b0 4
b0 6
b100 #
b100 2
b100 :
b0 $
b0 3
b0 8
1'
#345000
0'
#346000
0.
0,
01
0/
b1001 $
b1001 3
b1001 8
b11 #
b11 2
b11 :
b1001 %
b1001 4
b1001 6
1'
#347000
0'
#348000
b1000 %
b1000 4
b1000 6
b10 #
b10 2
b10 :
b1000 $
b1000 3
b1000 8
1'
#349000
0'
#350000
b111 $
b111 3
b111 8
b1 #
b1 2
b1 :
b111 %
b111 4
b111 6
1'
#351000
0'
#352000
10
1-
b110 %
b110 4
b110 6
b0 #
b0 2
b0 :
b110 $
b110 3
b110 8
1'
#353000
0'
#354000
00
0-
b101 $
b101 3
b101 8
b101 #
b101 2
b101 :
b101 %
b101 4
b101 6
1'
#355000
0'
#356000
b100 %
b100 4
b100 6
b100 #
b100 2
b100 :
b100 $
b100 3
b100 8
1'
#357000
0'
#358000
b11 $
b11 3
b11 8
b11 #
b11 2
b11 :
b11 %
b11 4
b11 6
1'
#359000
0'
#360000
b10 %
b10 4
b10 6
b10 #
b10 2
b10 :
b10 $
b10 3
b10 8
1'
#361000
0'
#362000
b1 $
b1 3
b1 8
b1 #
b1 2
b1 :
b1 %
b1 4
b1 6
1'
#363000
0'
#364000
1"
1,
10
1.
1/
1-
11
b0 %
b0 4
b0 6
b0 #
b0 2
b0 :
b0 $
b0 3
b0 8
1'
#365000
0'
#366000
0"
0.
00
0,
01
0-
0/
b1001 $
b1001 3
b1001 8
b101 #
b101 2
b101 :
b1001 %
b1001 4
b1001 6
1'
#367000
0'
#368000
b1000 %
b1000 4
b1000 6
b100 #
b100 2
b100 :
b1000 $
b1000 3
b1000 8
1'
#369000
0'
#370000
b111 $
b111 3
b111 8
b11 #
b11 2
b11 :
b111 %
b111 4
b111 6
1'
#371000
0'
#372000
b110 %
b110 4
b110 6
b10 #
b10 2
b10 :
b110 $
b110 3
b110 8
1'
#373000
0'
#374000
b101 $
b101 3
b101 8
b1 #
b1 2
b1 :
b101 %
b101 4
b101 6
1'
#375000
0'
#376000
10
1-
b100 %
b100 4
b100 6
b0 #
b0 2
b0 :
b100 $
b100 3
b100 8
1'
#377000
0'
#378000
00
0-
b11 $
b11 3
b11 8
b101 #
b101 2
b101 :
b11 %
b11 4
b11 6
1'
#379000
0'
#380000
b10 %
b10 4
b10 6
b100 #
b100 2
b100 :
b10 $
b10 3
b10 8
1'
#381000
0'
#382000
b1 $
b1 3
b1 8
b11 #
b11 2
b11 :
b1 %
b1 4
b1 6
1'
#383000
0'
