nivel1/nivel_2/timer_e_controle/nivel3/codificador/codificador_prioritario.v
module codificador_prioritario(entrada, enablen, BCD);
input wire [9:0]entrada;
input wire enablen;
output reg[3:0]BCD;

always@(entrada)
    if (enablen == 1'b0)
        begin
        case(entrada)
            10'b1000000000: BCD = 4'b1001;
            10'b0100000000: BCD = 4'b1000;
            10'b0010000000: BCD = 4'b0111;
            10'b0001000000: BCD = 4'b0110;
            10'b0000100000: BCD = 4'b0101;
            10'b0000010000: BCD = 4'b0100;
            10'b0000001000: BCD = 4'b0011;
            10'b0000000100: BCD = 4'b0010;
            10'b0000000010: BCD = 4'b0001;
            10'b0000000001: BCD = 4'b0000;
        endcase
    end

endmodule

codificador_prioritario/codificador_prioritario.tb.v
`timescale 1ns/1ns


module codificador_prioritario_teste;
    reg [9:0]entrada;
    reg enablen;
    wire [3:0]BCD;

        codificador_prioritario DUT(entrada, enablen, BCD);
    
    initial 
        begin

            $dumpfile("codificador_prioritario_teste.vcd");
            $dumpvars(0, codificador_prioritario_teste);

            entrada=10'b1000000000; enablen=0;
            #5  entrada=10'b0100000000; enablen=0; 
           	#5  entrada=10'b0010000000; enablen=0;
          	#5  entrada=10'b0001000000; enablen=0;
          	#5  entrada=10'b0000100000; enablen=0;
          	#5  entrada=10'b0000010000; enablen=0;
          	#5  entrada=10'b0000001000; enablen=0;
            #5  entrada=10'b0000000100; enablen=0;
          	#5  entrada=10'b0000000010; enablen=0;
            #5  entrada=10'b0000000001; enablen=0;

            #5  entrada=10'b1000000000; enablen=1;
            #5  entrada=10'b0100000000; enablen=1; 
           	#5  entrada=10'b0010000000; enablen=1;
          	#5  entrada=10'b0001000000; enablen=1;
          	#5  entrada=10'b0000100000; enablen=1;
          	#5  entrada=10'b0000010000; enablen=1;
          	#5  entrada=10'b0000001000; enablen=1;
            #5  entrada=10'b0000000100; enablen=1;
          	#5  entrada=10'b0000000010; enablen=1;
            #5  entrada=10'b0000000001; enablen=1;

            #5 entrada = 10'b1000000001; enablen=0;
            #5 entrada = 10'b1000001001; enablen=0;
            #5 entrada = 10'b1000000001; enablen=1;
            #5 entrada = 10'b1000001001; enablen=1;
        end
endmodule

nivel1/nivel_2/timer_e_controle/nivel3/codificador/codificador_prioritario_teste.vcd
$date
	Thu Apr 20 18:03:38 2023
$end
$version
	Icarus Verilog
$end
$timescale
	1ns
$end
$scope module codificador_prioritario_teste $end
$var wire 4 ! BCD [3:0] $end
$var reg 1 " enablen $end
$var reg 10 # entrada [9:0] $end
$scope module DUT $end
$var wire 1 " enablen $end
$var wire 10 $ entrada [9:0] $end
$var reg 4 % BCD [3:0] $end
$upscope $end
$upscope $end
$enddefinitions $end
$comment Show the parameter values. $end
$dumpall
$end
#0
$dumpvars
b1001 %
b1000000000 $
b1000000000 #
0"
b1001 !
$end
#5
b1000 !
b1000 %
b100000000 #
b100000000 $
#10
b111 !
b111 %
b10000000 #
b10000000 $
#15
b110 !
b110 %
b1000000 #
b1000000 $
#20
b101 !
b101 %
b100000 #
b100000 $
#25
b100 !
b100 %
b10000 #
b10000 $
#30
b11 !
b11 %
b1000 #
b1000 $
#35
b10 !
b10 %
b100 #
b100 $
#40
b10 #
b10 $
#45
b1 !
b1 %
b1 #
b1 $
#50
1"
b1000000000 #
b1000000000 $
#55
b100000000 #
b100000000 $
#60
b10000000 #
b10000000 $
#65
b1000000 #
b1000000 $
#70
b100000 #
b100000 $
#75
b10000 #
b10000 $
#80
b1000 #
b1000 $
#85
b100 #
b100 $
#90
b10 #
b10 $
#95
b1 #
b1 $
#100
0"
b1000000001 #
b1000000001 $
#105
b1000001001 #
b1000001001 $
#110
1"
b1000000001 #
b1000000001 $
#115
b1000001001 #
b1000001001 $
