contador_mod_6/contador_mod_6.v
module contador_mod_6(data, clk, loadn, en, clearn, tens, tc, zero);
  input wire [3:0] data;
  input wire clk, loadn, en, clearn;
  output reg [3:0] tens;
  output wire tc;
  output wire zero;

  always @ (negedge clearn)
  begin
    tens = 4'b0000;
  end

  assign zero = (tens == 4'b0000) ? 1'b1 : 1'b0;
  assign tc = en & zero;

  always @ (posedge clk)
  begin
    if (en) 
      case (tens)
        4'b0101: begin
          tens <= 4'b0100;
        end // 5 -> 4
        4'b0001: begin 
          tens <= 4'b0000;
        end  // 1 -> 0
        4'b0000: begin
          tens <= 4'b0101;
        end // 0 -> 5
        default: tens <= tens - 4'b0001;
      endcase

    else begin

      if(!loadn)
        tens <= data;
    end
  end
endmodule

contador_mod_6/contador_mod6.tb.v
`timescale 1ns/1ps

module contador_mod6_teste;

    reg [3:0] data; 
  	reg loadn, clearn, clk, en;
  	wire [3:0] tens; 
  	wire tc;
    wire zero;
  	integer i;
  

  	contador_mod_6 dut(data, loadn, clearn, clk, en, tens, tc, zero);

	initial
		begin
		
			$dumpfile("contador_mod6_teste.vcd");
			$dumpvars(0,contador_mod6_teste);
      
      assign loadn = 1;
      assign en = 0; 
      assign clearn = 1;
      assign data = 4'b0110;

      #5 assign loadn = 0;

      #5 assign loadn = 1;

      #5 assign en = 1; 
    end
  
  initial
    
    begin
    	clk = 1'b0;
  	end
		
  initial
    begin
    	#5 clk = ~clk;
      for(i = 0; i < 26; i= i + 1)
        begin
          #5 clk = ~clk;
        end
      
    end
    
endmodule

nivel1/nivel_2/minutos_segundos/nivel3/contador_mod6/contador_mod6_teste.vcd
$date
	Sun Apr 23 17:39:26 2023
$end
$version
	Icarus Verilog
$end
$timescale
	1ps
$end
$scope module contador_mod6_teste $end
$var wire 1 ! zero $end
$var wire 4 " tens [3:0] $end
$var wire 1 # tc $end
$var reg 1 $ clearn $end
$var reg 1 % clk $end
$var reg 4 & data [3:0] $end
$var reg 1 ' en $end
$var reg 1 ( loadn $end
$var integer 32 ) i [31:0] $end
$scope module dut $end
$var wire 1 $ clearn $end
$var wire 1 % clk $end
$var wire 4 * data [3:0] $end
$var wire 1 ' en $end
$var wire 1 ( loadn $end
$var wire 1 # tc $end
$var wire 1 ! zero $end
$var reg 4 + tens [3:0] $end
$upscope $end
$upscope $end
$enddefinitions $end
$comment Show the parameter values. $end
$dumpall
$end
#0
$dumpvars
bx +
b110 *
bx )
1(
0'
b110 &
0%
1$
0#
bx "
x!
$end
#5000
0!
b110 "
b110 +
b0 )
1%
0(
#10000
b1 )
0%
1(
#15000
b101 "
b101 +
b10 )
1%
1'
#20000
b11 )
0%
#25000
b100 "
b100 +
b100 )
1%
#30000
b101 )
0%
#35000
b11 "
b11 +
b110 )
1%
#40000
b111 )
0%
#45000
b10 "
b10 +
b1000 )
1%
#50000
b1001 )
0%
#55000
b1 "
b1 +
b1010 )
1%
#60000
b1011 )
0%
#65000
1#
1!
b0 "
b0 +
b1100 )
1%
#70000
b1101 )
0%
#75000
0#
0!
b101 "
b101 +
b1110 )
1%
#80000
b1111 )
0%
#85000
b100 "
b100 +
b10000 )
1%
#90000
b10001 )
0%
#95000
b11 "
b11 +
b10010 )
1%
#100000
b10011 )
0%
#105000
b10 "
b10 +
b10100 )
1%
#110000
b10101 )
0%
#115000
b1 "
b1 +
b10110 )
1%
#120000
b10111 )
0%
#125000
1#
1!
b0 "
b0 +
b11000 )
1%
#130000
b11001 )
0%
#135000
0#
0!
b101 "
b101 +
b11010 )
1%
