contador_nao_reciclavel/contador_nao_reciclavel.v
module counter(input wire clock, reset,output reg Q);

    reg [2:0] contador;
    always@(posedge clock or posedge reset)
    begin    
        if(reset)
            begin
                contador = 3'b000;
                Q = 0;
            end
        else if (contador == 3'b011)
            begin
                Q = 1;
                contador = contador + 1'b1;
            end
        else if (contador < 3'b111)
            begin
                contador = contador + 1'b1;
            end
    end
endmodule

nivel1/nivel_2/timer_e_controle/nivel3/contador_nao_reciclado/contador_nao_reciclavel.tb.v
`timescale 1ns/1ns

module test_contador;

    reg clock, clear, contador;
  	wire  Q;

  	counter dut(clock, clear, Q);

    initial
        begin

            $dumpfile("test_contador.vcd");
            $dumpvars(0, test_contador);

                clock = 1; clear=1; contador = 0;
            #5   contador = 3;
            #5   clear = 0; 
          
            repeat(16)
                begin
                    #10 clock = ~clock;
                end

        end
endmodule

nivel1/nivel_2/timer_e_controle/nivel3/contador_nao_reciclado/test_contador.vcd
$date
	Mon Apr 24 20:43:25 2023
$end
$version
	Icarus Verilog
$end
$timescale
	1ns
$end
$scope module test_contador $end
$var wire 1 ! Q $end
$var reg 1 " clear $end
$var reg 1 # clock $end
$var reg 1 $ contador $end
$scope module dut $end
$var wire 1 # clock $end
$var wire 1 " reset $end
$var reg 1 ! Q $end
$var reg 3 % contador [2:0] $end
$upscope $end
$upscope $end
$enddefinitions $end
$comment Show the parameter values. $end
$dumpall
$end
#0
$dumpvars
b0 %
0$
1#
1"
0!
$end
#5
1$
#10
0"
#20
0#
#30
b1 %
1#
#40
0#
#50
b10 %
1#
#60
0#
#70
b11 %
1#
#80
0#
#90
b100 %
1!
1#
#100
0#
#110
b101 %
1#
#120
0#
#130
b110 %
1#
#140
0#
#150
b111 %
1#
