nivel1/nivel2/magnetron/nivel_3/latch/latch.v
module latch_sr(input S, input R, 
                output reg Q);

always@*
    if (S && !R) //Set
        Q <= 1'b1;
    else if (R && !S) //Reset
        Q <= 1'b0;

endmodule

nivel1/nivel2/magnetron/nivel_3/bloco_logico/bloco_logico.v
module controle(input wire startn, stopn, clearn, door_closed, timer_done,
                output wire set, reset);

  assign set = (~startn) & door_closed & (~timer_done);
  assign reset = (~door_closed) | (~clearn) | (~stopn) | timer_done;

endmodule

nivel1/nivel2/magnetron/nivel2_magnetron.v
`include "./nivel_3/latch/latch.v"
`include "./nivel_3/bloco_logico/bloco_logico.v"

module nvl2_controle(startn, stopn, clearn, door_closed, timer_done, mag_on);
  input wire startn, stopn, clearn, door_closed, timer_done;
  output wire mag_on;

  wire set;
  wire reset;

  controle AL0(startn, stopn, clearn, door_closed, timer_done, set, reset);
  latch_sr AL1(set, reset, mag_on);
endmodule

nivel1/nivel2/magnetron/nivel2_magnetron.tb.v
`timescale 1ns/1ns

module test_control_nvl2;

    reg startn, stopn, clearn, door_closed, timer_done;
  	wire  mag_on;
  	nvl2_controle dut(startn, stopn, clearn, door_closed, timer_done, mag_on);

    initial
        begin

            $dumpfile("teste_magnetron_nvl2.vcd");
            $dumpvars(0, test_control_nvl2);

                startn=1; stopn=0; clearn=0; door_closed=0; timer_done=0;
            #5  startn=1; stopn=0; clearn=0; door_closed=1; timer_done=0;
         	  #5  startn=1; stopn=1; clearn=0; door_closed=1; timer_done=0;
            #5  startn=1; stopn=0; clearn=0; door_closed=1; timer_done=0;
            #5  startn=1; stopn=0; clearn=0; door_closed=0; timer_done=0;
            #5  startn=1; stopn=0; clearn=0; door_closed=1; timer_done=1;
            #5  startn=1; stopn=0; clearn=0; door_closed=1; timer_done=0;
          	#5  startn=1; stopn=0; clearn=1; door_closed=1; timer_done=1;
            #5  startn=1; stopn=0; clearn=0; door_closed=1; timer_done=0;
          	#5  startn=1; stopn=1; clearn=1; door_closed=1; timer_done=1;
            #5  startn=0; stopn=1; clearn=1; door_closed=1; timer_done=1;
            #5  startn=0; stopn=0; clearn=0; door_closed=0; timer_done=0;
          
        end
endmodule

nivel1/nivel2/magnetron/teste_magnetron_nvl2.vcd
$date
	Sun Apr 23 11:10:33 2023
$end
$version
	Icarus Verilog
$end
$timescale
	1ns
$end
$scope module test_control_nvl2 $end
$var wire 1 ! mag_on $end
$var reg 1 " clearn $end
$var reg 1 # door_closed $end
$var reg 1 $ startn $end
$var reg 1 % stopn $end
$var reg 1 & timer_done $end
$scope module dut $end
$var wire 1 " clearn $end
$var wire 1 # door_closed $end
$var wire 1 $ startn $end
$var wire 1 % stopn $end
$var wire 1 & timer_done $end
$var wire 1 ' set $end
$var wire 1 ( reset $end
$var wire 1 ! mag_on $end
$scope module AL0 $end
$var wire 1 " clearn $end
$var wire 1 # door_closed $end
$var wire 1 ( reset $end
$var wire 1 ' set $end
$var wire 1 $ startn $end
$var wire 1 % stopn $end
$var wire 1 & timer_done $end
$upscope $end
$scope module AL1 $end
$var wire 1 ( R $end
$var wire 1 ' S $end
$var reg 1 ! Q $end
$upscope $end
$upscope $end
$upscope $end
$enddefinitions $end
$comment Show the parameter values. $end
$dumpall
$end
#0
$dumpvars
1(
0'
0&
0%
1$
0#
0"
0!
$end
#5
1#
#10
1%
#15
0%
#20
0#
#25
1&
1#
#30
0&
#35
1&
1"
#40
0&
0"
#45
1&
1"
1%
#50
0$
#55
1(
0&
0#
0"
0%
