nivel1/nivel2/timer_e_controle/nivel3/mux/mux.v
module mux(input wire sel, saida_atraso, hz_clock,
                output reg Q);

    always@*
    if(sel == 0)
        begin
            Q = saida_atraso;
        end
    else
        Q = hz_clock;
endmodule

multiplexador/multiplexador.tb.v
`timescale 1ns/1ns

module test_mux;

    reg sel, saida_atraso, hz_clock;
  	wire  Q;

  	mux DUT(sel, saida_atraso, hz_clock, Q);

    initial
        begin

            $dumpfile("test_mux.vcd");
            $dumpvars(0, test_mux);

                sel=1; saida_atraso=0; hz_clock=1;
            #5  sel=0; saida_atraso=0; hz_clock=1;
         	  #5  sel=1; saida_atraso=1; hz_clock=0;
          	#5  sel=0; saida_atraso=1; hz_clock=0;
            #5  sel=1; saida_atraso=1; hz_clock=1;
          	#5  sel=0; saida_atraso=1; hz_clock=1;
            #5  sel=1; saida_atraso=0; hz_clock=0;
          	#5  sel=0; saida_atraso=0; hz_clock=0;
          
        end
endmodule

nivel1/nivel_2/timer_e_controle/nivel3/mux/test_mux.vcd
$date
	Sun Apr 23 17:45:20 2023
$end
$version
	Icarus Verilog
$end
$timescale
	1ns
$end
$scope module test_mux $end
$var wire 1 ! Q $end
$var reg 1 " hz_clock $end
$var reg 1 # saida_atraso $end
$var reg 1 $ sel $end
$scope module DUT $end
$var wire 1 " hz_clock $end
$var wire 1 # saida_atraso $end
$var wire 1 $ sel $end
$var reg 1 ! Q $end
$upscope $end
$upscope $end
$enddefinitions $end
$comment Show the parameter values. $end
$dumpall
$end
#0
$dumpvars
1$
0#
1"
1!
$end
#5
0!
0$
#10
0"
1#
1$
#15
1!
0$
#20
1"
1$
#25
0$
#30
0!
0"
0#
1$
#35
0$
