contador_mod10/contador_mod10.v
module contador_mod10 (data, clk, load, enable, clear, count, count_end, tc);
  input wire [3:0] data;
  input wire clk, load, enable, clear;
  output reg [3:0] count;
  output wire count_end;
  output wire tc;

  always @ (negedge clear)
  begin
    count <= 4'b0000;
  end
  assign tc = enable & count_end;
  always @ (posedge clk)
  begin
    if (enable) begin
      case (count)
        4'b0000: count <= 4'b1001;
        default: count <= count - 4'b0001;
      endcase
    end
    else begin
      if (!load) begin
        count <= data;
      end
    end
  end
  
  assign count_end = (count == 4'b0000) ? 1'b1 : 1'b0;
endmodule

timer_nivel2/contador_mod10/contador_mod10t.tb.v
`timescale 1ns/1ps

module contador_mod10t;

 	reg [3:0] data; 
  	reg clk, load, en, clearn;
  	wire [3:0] count; 
    wire count_end;
    wire tc;
  	integer i;
  

  	contador_mod10 dut(data, clk, load, en, clearn, count, count_end, tc);

	initial
		begin
		
			$dumpfile("contador_mod10.vcd");
			$dumpvars(0, contador_mod10t);
          
      assign load = 1;
      assign en = 0; 
      assign clearn = 1;
      assign data = 4'b0110;

      #5 assign load = 0;

      #5 assign load = 1;

      #5 assign en = 1; 
    end
  
  initial
    
    begin
    	clk = 1'b0;
  	end
		
  initial
    begin
    	#5 clk = ~clk;
      for(i = 0; i < 26; i= i + 1)
        begin
          #5 clk = ~clk;
        end
      
    end
    
endmodule

nivel1/nivel_2/minutos_segundos/nivel3/contador_mod10/contador_mod10.vcd
$date
	Sun Apr 23 17:40:52 2023
$end
$version
	Icarus Verilog
$end
$timescale
	1ps
$end
$scope module contador_mod10t $end
$var wire 1 ! tc $end
$var wire 1 " count_end $end
$var wire 4 # count [3:0] $end
$var reg 1 $ clearn $end
$var reg 1 % clk $end
$var reg 4 & data [3:0] $end
$var reg 1 ' en $end
$var reg 1 ( load $end
$var integer 32 ) i [31:0] $end
$scope module dut $end
$var wire 1 $ clear $end
$var wire 1 % clk $end
$var wire 4 * data [3:0] $end
$var wire 1 ' enable $end
$var wire 1 ( load $end
$var wire 1 ! tc $end
$var wire 1 " count_end $end
$var reg 4 + count [3:0] $end
$upscope $end
$upscope $end
$enddefinitions $end
$comment Show the parameter values. $end
$dumpall
$end
#0
$dumpvars
bx +
b110 *
bx )
1(
0'
b110 &
0%
1$
bx #
x"
0!
$end
#5000
0"
b110 #
b110 +
b0 )
1%
0(
#10000
b1 )
0%
1(
#15000
b101 #
b101 +
b10 )
1%
1'
#20000
b11 )
0%
#25000
b100 #
b100 +
b100 )
1%
#30000
b101 )
0%
#35000
b11 #
b11 +
b110 )
1%
#40000
b111 )
0%
#45000
b10 #
b10 +
b1000 )
1%
#50000
b1001 )
0%
#55000
b1 #
b1 +
b1010 )
1%
#60000
b1011 )
0%
#65000
1!
1"
b0 #
b0 +
b1100 )
1%
#70000
b1101 )
0%
#75000
0!
0"
b1001 #
b1001 +
b1110 )
1%
#80000
b1111 )
0%
#85000
b1000 #
b1000 +
b10000 )
1%
#90000
b10001 )
0%
#95000
b111 #
b111 +
b10010 )
1%
#100000
b10011 )
0%
#105000
b110 #
b110 +
b10100 )
1%
#110000
b10101 )
0%
#115000
b101 #
b101 +
b10110 )
1%
#120000
b10111 )
0%
#125000
b100 #
b100 +
b11000 )
1%
#130000
b11001 )
0%
#135000
b11 #
b11 +
b11010 )
1%
