magnetron_nivel2/nivel_3/latch_sr/latch_sr.v
module latch_sr(input S, input R, 
                input clk, output reg Q);

always @(posedge clk) begin
    if (S && !R) //Set
        Q <= 1'b1;
    else if (R && !S) //Reset
        Q <= 1'b0;
end
endmodule

latch_sr/latch_sr.tb.v
`timescale 1ns/1ps

module test_latch;

    reg S, R, clk;
    wire Q;

    latch_sr DUT(S, R, clk, Q);

    initial begin
        $dumpfile("latch_teste.vcd");
        $dumpvars(0,test_latch);
            #10 S = 0; R = 0; clk = 0;

            #10 S = 0; R = 0; clk = 1;

            #10 S = 0; R = 1; clk = 0;

            #10 S = 0; R = 1; clk = 1;

            #10 S = 0; R = 0; clk = 0;

            #10 S = 0; R = 0; clk = 1;

            #10 S = 1; R = 0; clk = 0;

            #10 S = 1; R = 0; clk = 1;

            #10 S = 0; R = 0; clk = 0;

            #10 S = 0; R = 0; clk = 1;

            #10 S = 1; R = 1; clk = 0;

            #10 S = 1; R = 1; clk = 1;

            #10 S = 0; R = 0; clk = 0;

            #10 S = 0; R = 0; clk = 1;

            #10;
    end
endmodule

magnetron_nivel2/nivel_3/latch_sr/latch_teste.vcd
$date
	Fri Apr 21 15:11:18 2023
$end
$version
	Icarus Verilog
$end
$timescale
	1ps
$end
$scope module test_latch $end
$var wire 1 ! Q $end
$var reg 1 " R $end
$var reg 1 # S $end
$var reg 1 $ clk $end
$scope module DUT $end
$var wire 1 " R $end
$var wire 1 # S $end
$var wire 1 $ clk $end
$var reg 1 ! Q $end
$upscope $end
$upscope $end
$enddefinitions $end
$comment Show the parameter values. $end
$dumpall
$end
#0
$dumpvars
x$
x#
x"
x!
$end
#10000
0$
0"
0#
#20000
1$
#30000
0$
1"
#40000
0!
1$
#50000
0$
0"
#60000
1$
#70000
0$
1#
#80000
1!
1$
#90000
0$
0#
#100000
1$
#110000
0$
1"
1#
#120000
1$
#130000
0$
0"
0#
