nivel1/nivel2/entrada_timer/nivel3/contador_freq/div_frequencia.v
module divisor(input clk,
            output reg clkf);
  reg [5:0] a = 6'b000000;
  initial clkf = 1'b0;
  
  always@(posedge clk)
    begin
      a = a + 1'b1;
      
      if(a >= 50)
        begin
          a = 6'b000000;
          clkf = ~clkf;
        end
    end
endmodule

divisor/divisor.tb.v
`timescale 1ns/1ps

module test_divisor;
   reg clk;
   wire clkf;

   divisor dut(clk,clkf);
  
  initial
    begin

        $dumpfile("divisor_teste.vcd");
        $dumpvars(0, test_divisor);
            #1 clk = 1'b0;

            repeat(200)
                #1 clk = ~clk;
    end


endmodule

divisor/divisor_teste.vcd
$date
	Thu Apr 20 17:41:29 2023
$end
$version
	Icarus Verilog
$end
$timescale
	1ps
$end
$scope module test_divisor $end
$var wire 1 ! clkf $end
$var reg 1 " clk $end
$scope module dut $end
$var wire 1 " clk $end
$var reg 6 # a [5:0] $end
$var reg 1 ! clkf $end
$upscope $end
$upscope $end
$enddefinitions $end
$comment Show the parameter values. $end
$dumpall
$end
#0
$dumpvars
b0 #
x"
0!
$end
#1000
0"
#2000
b1 #
1"
#3000
0"
#4000
b10 #
1"
#5000
0"
#6000
b11 #
1"
#7000
0"
#8000
b100 #
1"
#9000
0"
#10000
b101 #
1"
#11000
0"
#12000
b110 #
1"
#13000
0"
#14000
b111 #
1"
#15000
0"
#16000
b1000 #
1"
#17000
0"
#18000
b1001 #
1"
#19000
0"
#20000
b1010 #
1"
#21000
0"
#22000
b1011 #
1"
#23000
0"
#24000
b1100 #
1"
#25000
0"
#26000
b1101 #
1"
#27000
0"
#28000
b1110 #
1"
#29000
0"
#30000
b1111 #
1"
#31000
0"
#32000
b10000 #
1"
#33000
0"
#34000
b10001 #
1"
#35000
0"
#36000
b10010 #
1"
#37000
0"
#38000
b10011 #
1"
#39000
0"
#40000
b10100 #
1"
#41000
0"
#42000
b10101 #
1"
#43000
0"
#44000
b10110 #
1"
#45000
0"
#46000
b10111 #
1"
#47000
0"
#48000
b11000 #
1"
#49000
0"
#50000
b11001 #
1"
#51000
0"
#52000
b11010 #
1"
#53000
0"
#54000
b11011 #
1"
#55000
0"
#56000
b11100 #
1"
#57000
0"
#58000
b11101 #
1"
#59000
0"
#60000
b11110 #
1"
#61000
0"
#62000
b11111 #
1"
#63000
0"
#64000
b100000 #
1"
#65000
0"
#66000
b100001 #
1"
#67000
0"
#68000
b100010 #
1"
#69000
0"
#70000
b100011 #
1"
#71000
0"
#72000
b100100 #
1"
#73000
0"
#74000
b100101 #
1"
#75000
0"
#76000
b100110 #
1"
#77000
0"
#78000
b100111 #
1"
#79000
0"
#80000
b101000 #
1"
#81000
0"
#82000
b101001 #
1"
#83000
0"
#84000
b101010 #
1"
#85000
0"
#86000
b101011 #
1"
#87000
0"
#88000
b101100 #
1"
#89000
0"
#90000
b101101 #
1"
#91000
0"
#92000
b101110 #
1"
#93000
0"
#94000
b101111 #
1"
#95000
0"
#96000
b110000 #
1"
#97000
0"
#98000
b110001 #
1"
#99000
0"
#100000
1!
b0 #
1"
#101000
0"
#102000
b1 #
1"
#103000
0"
#104000
b10 #
1"
#105000
0"
#106000
b11 #
1"
#107000
0"
#108000
b100 #
1"
#109000
0"
#110000
b101 #
1"
#111000
0"
#112000
b110 #
1"
#113000
0"
#114000
b111 #
1"
#115000
0"
#116000
b1000 #
1"
#117000
0"
#118000
b1001 #
1"
#119000
0"
#120000
b1010 #
1"
#121000
0"
#122000
b1011 #
1"
#123000
0"
#124000
b1100 #
1"
#125000
0"
#126000
b1101 #
1"
#127000
0"
#128000
b1110 #
1"
#129000
0"
#130000
b1111 #
1"
#131000
0"
#132000
b10000 #
1"
#133000
0"
#134000
b10001 #
1"
#135000
0"
#136000
b10010 #
1"
#137000
0"
#138000
b10011 #
1"
#139000
0"
#140000
b10100 #
1"
#141000
0"
#142000
b10101 #
1"
#143000
0"
#144000
b10110 #
1"
#145000
0"
#146000
b10111 #
1"
#147000
0"
#148000
b11000 #
1"
#149000
0"
#150000
b11001 #
1"
#151000
0"
#152000
b11010 #
1"
#153000
0"
#154000
b11011 #
1"
#155000
0"
#156000
b11100 #
1"
#157000
0"
#158000
b11101 #
1"
#159000
0"
#160000
b11110 #
1"
#161000
0"
#162000
b11111 #
1"
#163000
0"
#164000
b100000 #
1"
#165000
0"
#166000
b100001 #
1"
#167000
0"
#168000
b100010 #
1"
#169000
0"
#170000
b100011 #
1"
#171000
0"
#172000
b100100 #
1"
#173000
0"
#174000
b100101 #
1"
#175000
0"
#176000
b100110 #
1"
#177000
0"
#178000
b100111 #
1"
#179000
0"
#180000
b101000 #
1"
#181000
0"
#182000
b101001 #
1"
#183000
0"
#184000
b101010 #
1"
#185000
0"
#186000
b101011 #
1"
#187000
0"
#188000
b101100 #
1"
#189000
0"
#190000
b101101 #
1"
#191000
0"
#192000
b101110 #
1"
#193000
0"
#194000
b101111 #
1"
#195000
0"
#196000
b110000 #
1"
#197000
0"
#198000
b110001 #
1"
#199000
0"
#200000
0!
b0 #
1"
