nivel1/nivel_2/decoder/decoder_7seg.v
module decoder(min, dSec, sec, minOut, dsecOut, secOut);
    input wire [3:0] min, dSec, sec;
    output reg [6:0] minOut, dsecOut, secOut;

  always@(min)
    case(min)
      4'b0000 : minOut = 7'b1111110;
      4'b0001 : minOut = 7'b0110000;
      4'b0010 : minOut = 7'b1101101;
      4'b0011 : minOut = 7'b1111001;
      4'b0100 : minOut = 7'b0110011;
      4'b0101 : minOut = 7'b1011011;
      4'b0110 : minOut = 7'b1011111;
      4'b0111 : minOut = 7'b1110010;
      4'b1000 : minOut = 7'b1111111;
      4'b1001 : minOut = 7'b1111011;
    endcase
  
  always@(dSec)
  case(dSec)
      4'b0000 : dsecOut = 7'b1111110;
      4'b0001 : dsecOut = 7'b0110000;
      4'b0010 : dsecOut = 7'b1101101;
      4'b0011 : dsecOut = 7'b1111001;
      4'b0100 : dsecOut = 7'b0110011;
      4'b0101 : dsecOut = 7'b1011011;
      4'b0110 : dsecOut = 7'b1011111;
      4'b0111 : dsecOut = 7'b1110010;
      4'b1000 : dsecOut = 7'b1111111;
      4'b1001 : dsecOut = 7'b1111011;
    endcase
  
  always@(sec)
  case(sec)
      4'b0000 : secOut = 7'b1111110;
      4'b0001 : secOut = 7'b0110000;
      4'b0010 : secOut = 7'b1101101;
      4'b0011 : secOut = 7'b1111001;
      4'b0100 : secOut = 7'b0110011;
      4'b0101 : secOut = 7'b1011011;
      4'b0110 : secOut = 7'b1011111;
      4'b0111 : secOut = 7'b1110010;
      4'b1000 : secOut = 7'b1111111;
      4'b1001 : secOut = 7'b1111011;
    endcase

endmodule

nivel1/nivel_2/decoder/decoder_7seg.tb.v
`timescale 1ns/1ns

module test_decoder;

    reg [3:0] min, dSec, sec;
  	wire [6:0] minOut, dsecOut, secOut;

  	decoder DUT(.min(min), .dSec(dSec), .sec(sec), .minOut(minOut), .dsecOut(dsecOut), .secOut(secOut));

    initial
        begin

            $dumpfile("test_decoder.vcd");
            $dumpvars(0, test_decoder);

                min=4'b0000; dSec=4'b0000; sec=4'b0000;  
            #5  min=4'b0001; dSec=4'b0001; sec=4'b0001; 
         	  #5  min=4'b0010; dSec=4'b0010; sec=4'b0010;
            #5  min=4'b0011; dSec=4'b0011; sec=4'b0011;
            #5  min=4'b0100; dSec=4'b0100; sec=4'b0100;
            #5  min=4'b0101; dSec=4'b0101; sec=4'b0101;
          	#5  min=4'b0110; dSec=4'b0110; sec=4'b0110;
            #5  min=4'b0111; dSec=4'b0111; sec=4'b0111;
          	#5  min=4'b1000; dSec=4'b1000; sec=4'b1000;
            #5  min=4'b1001; dSec=4'b1001; sec=4'b1001;    
        end
endmodule

nivel1/nivel_2/decoder/test_decoder.vcd
$date
	Sun Apr 23 17:38:27 2023
$end
$version
	Icarus Verilog
$end
$timescale
	1ns
$end
$scope module test_decoder $end
$var wire 7 ! secOut [6:0] $end
$var wire 7 " minOut [6:0] $end
$var wire 7 # dsecOut [6:0] $end
$var reg 4 $ dSec [3:0] $end
$var reg 4 % min [3:0] $end
$var reg 4 & sec [3:0] $end
$scope module dut $end
$var wire 4 ' dSec [3:0] $end
$var wire 4 ( min [3:0] $end
$var wire 4 ) sec [3:0] $end
$var reg 7 * dsecOut [6:0] $end
$var reg 7 + minOut [6:0] $end
$var reg 7 , secOut [6:0] $end
$upscope $end
$upscope $end
$enddefinitions $end
$comment Show the parameter values. $end
$dumpall
$end
#0
$dumpvars
b1 ,
b1 +
b1 *
b0 )
b0 (
b0 '
b0 &
b0 %
b0 $
b1 #
b1 "
b1 !
$end
#5
b1001111 !
b1001111 ,
b1001111 #
b1001111 *
b1001111 "
b1001111 +
b1 &
b1 )
b1 $
b1 '
b1 %
b1 (
#10
b10010 !
b10010 ,
b10010 #
b10010 *
b10010 "
b10010 +
b10 &
b10 )
b10 $
b10 '
b10 %
b10 (
#15
b110 !
b110 ,
b110 #
b110 *
b110 "
b110 +
b11 &
b11 )
b11 $
b11 '
b11 %
b11 (
#20
b1001100 !
b1001100 ,
b1001100 #
b1001100 *
b1001100 "
b1001100 +
b100 &
b100 )
b100 $
b100 '
b100 %
b100 (
#25
b100100 !
b100100 ,
b100100 #
b100100 *
b100100 "
b100100 +
b101 &
b101 )
b101 $
b101 '
b101 %
b101 (
#30
b100000 !
b100000 ,
b100000 #
b100000 *
b100000 "
b100000 +
b110 &
b110 )
b110 $
b110 '
b110 %
b110 (
#35
b1101 !
b1101 ,
b1101 #
b1101 *
b1101 "
b1101 +
b111 &
b111 )
b111 $
b111 '
b111 %
b111 (
#40
b0 !
b0 ,
b0 #
b0 *
b0 "
b0 +
b1000 &
b1000 )
b1000 $
b1000 '
b1000 %
b1000 (
#45
b100 !
b100 ,
b100 #
b100 *
b100 "
b100 +
b1001 &
b1001 )
b1001 $
b1001 '
b1001 %
b1001 (
