nivel1/nivel2/magnetron/nivel_3/bloco_logico/bloco_logico.v
module controle(input wire startn, stopn, clearn, door_closed, timer_done,
                output wire set, reset);

  assign set = (~startn) & door_closed & (~timer_done);
  assign reset = (~door_closed) | (~clearn) | (~stopn) | timer_done;

endmodule

nivel1/nivel_2/controle_magnetron/nivel_3/bloco_logico/bloco_logico.tb.v
`timescale 1ns/1ns

module test_bloco_logico;

    reg startn, stopn, clearn, door_closed, timer_done;
  	wire  set, reset;

  	controle dut(startn, stopn, clearn, door_closed, timer_done, set, reset);

    initial
        begin

            $dumpfile("test_bloco_logico.vcd");
            $dumpvars(0, test_bloco_logico);

                startn=1; stopn=0; clearn=0; door_closed=0; timer_done=0;
            #5  startn=1; stopn=0; clearn=0; door_closed=1; timer_done=0;
         	  #5  startn=1; stopn=1; clearn=0; door_closed=1; timer_done=0;
            #5  startn=1; stopn=0; clearn=0; door_closed=1; timer_done=0;
            #5  startn=1; stopn=0; clearn=0; door_closed=1; timer_done=1;
            #5  startn=1; stopn=0; clearn=0; door_closed=0; timer_done=0;
          	#5  startn=1; stopn=0; clearn=1; door_closed=1; timer_done=1;
            #5  startn=1; stopn=0; clearn=0; door_closed=1; timer_done=0;
          	#5  startn=1; stopn=1; clearn=1; door_closed=1; timer_done=1;
            #5  startn=0; stopn=1; clearn=1; door_closed=1; timer_done=1;
            #5  startn=0; stopn=0; clearn=0; door_closed=0; timer_done=0;
            #5  startn=0; stopn=1; clearn=1; door_closed=1; timer_done=0;
          
        end
endmodule

nivel1/nivel_2/controle_magnetron/nivel_3/bloco_logico/test_bloco_logico.vcd
$date
	Sun Apr 23 17:34:55 2023
$end
$version
	Icarus Verilog
$end
$timescale
	1ns
$end
$scope module test_bloco_logico $end
$var wire 1 ! set $end
$var wire 1 " reset $end
$var reg 1 # clearn $end
$var reg 1 $ door_closed $end
$var reg 1 % startn $end
$var reg 1 & stopn $end
$var reg 1 ' timer_done $end
$scope module dut $end
$var wire 1 # clearn $end
$var wire 1 $ door_closed $end
$var wire 1 " reset $end
$var wire 1 ! set $end
$var wire 1 % startn $end
$var wire 1 & stopn $end
$var wire 1 ' timer_done $end
$upscope $end
$upscope $end
$enddefinitions $end
$comment Show the parameter values. $end
$dumpall
$end
#0
$dumpvars
0'
0&
1%
0$
0#
1"
0!
$end
#5
1$
#10
1&
#15
0&
#20
1'
#25
0'
0$
#30
1'
1$
1#
#35
0'
0#
#40
1'
1#
1&
#45
0%
#50
1"
0'
0$
0#
0&
